srsinst/sr542/__init__.py
srsinst/sr542/__main__.py
srsinst/sr542/dutyFactorControl.taskconfig
srsinst/sr542/sr542 with sr860.taskconfig
srsinst/sr542/sr542.taskconfig
srsinst/sr542/instruments/components.py
srsinst/sr542/instruments/get_instruments.py
srsinst/sr542/instruments/keys.py
srsinst/sr542/instruments/sr542.py
srsinst/sr542/tasks/dutyfactorcontrol.py
srsinst.sr542-0.1.0.dist-info/LICENSE.txt
srsinst.sr542-0.1.0.dist-info/METADATA
srsinst.sr542-0.1.0.dist-info/WHEEL
srsinst.sr542-0.1.0.dist-info/entry_points.txt
srsinst.sr542-0.1.0.dist-info/top_level.txt
srsinst.sr542-0.1.0.dist-info/RECORD
