Metadata-Version: 2.1
Name: srsinst.sr542
Version: 0.1.0
Summary: Instrument driver package for precision optical chopper SR542 from Stanford Research Systems
Author: Chulhoon Kim, Andrew Berger
License: MIT license
Keywords: SR542,SRS,Stanford Research Systems,optical chopper
Classifier: Development Status :: 3 - Alpha
Classifier: Intended Audience :: Science/Research
Classifier: License :: OSI Approved :: MIT License
Classifier: Programming Language :: Python :: 3.7
Classifier: Programming Language :: Python :: 3.8
Classifier: Programming Language :: Python :: 3.9
Classifier: Programming Language :: Python :: 3.10
Classifier: Topic :: Scientific/Engineering
Requires-Python: >=3.7
License-File: LICENSE.txt
Requires-Dist: numpy
Requires-Dist: srsgui (>=0.4.0)
Provides-Extra: full
Requires-Dist: matplotlib (>=3.6.2) ; extra == 'full'
Requires-Dist: pyside6 ; extra == 'full'
